uniswaptool/__init__.py
uniswaptool/assets/erc20.abi
uniswaptool/assets/erc20b32.abi
uniswaptool/assets/uniswap-v1/exchange.abi
uniswaptool/assets/uniswap-v1/factory.abi
uniswaptool/assets/uniswap-v2/factory.abi
uniswaptool/assets/uniswap-v2/router02.abi
uniswaptool/assets/uniswap-v3/factory.abi
uniswaptool/assets/uniswap-v3/multicall.abi
uniswaptool/assets/uniswap-v3/nonFungiblePositionManager.abi
uniswaptool/assets/uniswap-v3/pool.abi
uniswaptool/assets/uniswap-v3/quoter.abi
uniswaptool/assets/uniswap-v3/router.abi
uniswaptool/cli.py
uniswaptool/constants.py
uniswaptool/decorators.py
uniswaptool/exceptions.py
uniswaptool/py.typed
uniswaptool/token.py
uniswaptool/tokens.py
uniswaptool/types.py
uniswaptool/uniswap.py
uniswaptool/util.py
uniswap_tool-0.2.0.dist-info/entry_points.txt
uniswap_tool-0.2.0.dist-info/LICENSE
uniswap_tool-0.2.0.dist-info/METADATA
uniswap_tool-0.2.0.dist-info/WHEEL
uniswap_tool-0.2.0.dist-info/RECORD
